mcp_seniverse_weather/__init__.py
mcp_seniverse_weather/__main__.py
mcp_seniverse_weather/server.py
mcp_seniverse_weather-1.0.0.dist-info/METADATA
mcp_seniverse_weather-1.0.0.dist-info/WHEEL
mcp_seniverse_weather-1.0.0.dist-info/entry_points.txt
mcp_seniverse_weather-1.0.0.dist-info/RECORD
